MANIFEST.in
setup.py
/home/root/libgpiod/bindings/python/gpiod/ext/chip.c
/home/root/libgpiod/bindings/python/gpiod/ext/common.c
/home/root/libgpiod/bindings/python/gpiod/ext/line-config.c
/home/root/libgpiod/bindings/python/gpiod/ext/line-settings.c
/home/root/libgpiod/bindings/python/gpiod/ext/module.c
/home/root/libgpiod/bindings/python/gpiod/ext/request.c
gpiod/__init__.py
gpiod/chip.py
gpiod/chip_info.py
gpiod/edge_event.py
gpiod/exception.py
gpiod/info_event.py
gpiod/internal.py
gpiod/line.py
gpiod/line_info.py
gpiod/line_request.py
gpiod/line_settings.py
gpiod/version.py
gpiod/ext/chip.c
gpiod/ext/common.c
gpiod/ext/internal.h
gpiod/ext/line-config.c
gpiod/ext/line-settings.c
gpiod/ext/module.c
gpiod/ext/request.c
libgpiod.egg-info/PKG-INFO
libgpiod.egg-info/SOURCES.txt
libgpiod.egg-info/dependency_links.txt
libgpiod.egg-info/top_level.txt
tests/__init__.py
tests/__main__.py
tests/helpers.py
tests/tests_chip.py
tests/tests_chip_info.py
tests/tests_edge_event.py
tests/tests_info_event.py
tests/tests_line_info.py
tests/tests_line_request.py
tests/tests_line_settings.py
tests/tests_module.py
tests/gpiosim/__init__.py
tests/gpiosim/chip.py
tests/gpiosim/ext.c
tests/procname/__init__.py
tests/procname/ext.c